{"id":"evmos","symbol":"evmos","name":"Evmos","asset_platform_id":null,"platforms":{"":"","evmos":"0xd4949664cd82660aae99bedc034a0dea8a0bd517","ethereum":"0x93581991f68dbae1ea105233b67f7fa0d6bdee7b"},"detail_platforms":{"":{"decimal_place":null,"contract_address":""},"evmos":{"decimal_place":18,"contract_address":"0xd4949664cd82660aae99bedc034a0dea8a0bd517"},"ethereum":{"decimal_place":18,"contract_address":"0x93581991f68dbae1ea105233b67f7fa0d6bdee7b"}},"block_time_in_minutes":0,"hashing_algorithm":null,"categories":["Ethereum Ecosystem","Cosmos Ecosystem"],"public_notice":null,"additional_notices":[],"description":{"en":"Evmos is the one of the first Ethereum Virtual Machine-based blockchains in the Cosmos ecosystem and enables developers to launch apps that run smart contracts across any number of EVM and Cosmos-based blockchains. It makes that process as simple and seamless as possible by allowing developers to continue creating apps in Solidity and Vyper like they’re accustomed to in the Ethereum ecosystem. Evmos opens a new frontier for blockchain applications, expanding the functionality of the EVM by enabling cross-chain applications that tap the liquidity and user bases of multiple blockchain ecosystems to provide more unified experiences."},"links":{"homepage":["http://evmos.org/","https://evmos.space/",""],"blockchain_site":["https://www.mintscan.io/evmos","https://evm.evmos.org/token/0xd4949664cd82660aae99bedc034a0dea8a0bd517","https://etherscan.io/token/0x93581991f68dbae1ea105233b67f7fa0d6bdee7b","https://ethplorer.io/address/0x93581991f68dbae1ea105233b67f7fa0d6bdee7b","https://evmos.explorers.guru/","","","","",""],"official_forum_url":["","",""],"chat_url":["https://discord.com/invite/evmos","",""],"announcement_url":["https://evmos.blog",""],"twitter_screen_name":"EvmosOrg","facebook_username":"","bitcointalk_thread_identifier":null,"telegram_channel_identifier":"EvmosOrg","subreddit_url":null,"repos_url":{"github":["https://github.com/tharsis/evmos"],"bitbucket":[]}},"image":{"thumb":"https://assets.coingecko.com/coins/images/24023/thumb/evmos.png?1653958927","small":"https://assets.coingecko.com/coins/images/24023/small/evmos.png?1653958927","large":"https://assets.coingecko.com/coins/images/24023/large/evmos.png?1653958927"},"country_origin":"","genesis_date":null,"sentiment_votes_up_percentage":55.17,"sentiment_votes_down_percentage":44.83,"watchlist_portfolio_users":29403,"market_cap_rank":398,"coingecko_rank":110,"coingecko_score":44.405,"developer_score":81.041,"community_score":9.855,"liquidity_score":33.213,"public_interest_score":0.055,"market_data":{"current_price":{"aed":0.348923,"ars":24.37,"aud":0.142575,"bch":0.00032337,"bdt":10.28,"bhd":0.0357773,"bmd":0.094996,"bnb":0.00039007,"brl":0.455012,"btc":3.11e-06,"cad":0.125854,"chf":0.084997,"clp":76.14,"cny":0.689073,"czk":2.07,"dkk":0.648296,"dot":0.01778618,"eos":0.12135904,"eth":4.935e-05,"eur":0.087021,"gbp":0.074762,"hkd":0.74445,"huf":32.46,"idr":1428.77,"ils":0.352374,"inr":7.8,"jpy":13.71,"krw":125.04,"kwd":0.02920937,"lkr":29.26,"ltc":0.00089227,"mmk":199.5,"mxn":1.63,"myr":0.443394,"ngn":72.22,"nok":1.02,"nzd":0.154766,"php":5.25,"pkr":27.22,"pln":0.386071,"rub":8.44,"sar":0.356312,"sek":1.025,"sgd":0.128454,"thb":3.35,"try":2.47,"twd":2.96,"uah":3.51,"usd":0.094996,"vef":0.00951195,"vnd":2239.77,"xag":0.0041718,"xau":4.949e-05,"xdr":0.071251,"xlm":0.88173643,"xrp":0.20117193,"yfi":1.432e-05,"zar":1.79,"bits":3.11,"link":0.01519431,"sats":310.62},"total_value_locked":null,"mcap_to_tvl_ratio":null,"fdv_to_tvl_ratio":null,"roi":null,"ath":{"aed":25.12,"ars":787.67,"aud":9.63,"bch":0.03543563,"bdt":590.83,"bhd":2.58,"bmd":6.84,"bnb":0.01682118,"brl":33.77,"btc":0.00020819,"cad":8.76,"chf":6.65,"clp":5866.95,"cny":45.31,"czk":159.94,"dkk":48.46,"dot":0.59674806,"eos":4.004209,"eth":0.00293456,"eur":6.51,"gbp":5.49,"hkd":53.66,"huf":2461.7,"idr":99258,"ils":22.76,"inr":523.72,"jpy":894.77,"krw":8700.42,"kwd":2.1,"lkr":2391.32,"ltc":0.08149844,"mmk":12650.05,"mxn":139.8,"myr":29.83,"ngn":2839.29,"nok":64.37,"nzd":10.54,"php":358.03,"pkr":1269.76,"pln":30.55,"rub":497.25,"sar":25.65,"sek":67.48,"sgd":6.61,"thb":235.56,"try":101.12,"twd":201.91,"uah":206.68,"usd":6.84,"vef":0.684675,"vnd":156976,"xag":0.290917,"xau":0.00360971,"xdr":4.98,"xlm":41.261955,"xrp":12.836551,"yfi":0.00049938,"zar":109.61,"bits":208.19,"link":0.65653019,"sats":20819},"ath_change_percentage":{"aed":-98.61165,"ars":-96.90847,"aud":-98.52018,"bch":-99.09112,"bdt":-98.26167,"bhd":-98.61302,"bmd":-98.61163,"bnb":-97.68351,"brl":-98.6536,"btc":-98.50909,"cad":-98.56382,"chf":-98.72197,"clp":-98.70312,"cny":-98.48017,"czk":-98.70746,"dkk":-98.6632,"dot":-97.02002,"eos":-96.97147,"eth":-98.32064,"eur":-98.66453,"gbp":-98.63955,"hkd":-98.61351,"huf":-98.68224,"idr":-98.56148,"ils":-98.45276,"inr":-98.51183,"jpy":-98.46861,"krw":-98.56372,"kwd":-98.60812,"lkr":-98.77711,"ltc":-98.90805,"mmk":-98.42392,"mxn":-98.8371,"myr":-98.51456,"ngn":-97.45796,"nok":-98.4159,"nzd":-98.53202,"php":-98.53435,"pkr":-97.85796,"pln":-98.73707,"rub":-98.30413,"sar":-98.61165,"sek":-98.48139,"sgd":-98.05666,"thb":-98.58038,"try":-97.55428,"twd":-98.53484,"uah":-98.30346,"usd":-98.61163,"vef":-98.61163,"vnd":-98.57409,"xag":-98.56691,"xau":-98.62988,"xdr":-98.56933,"xlm":-97.86531,"xrp":-98.4336,"yfi":-97.13427,"zar":-98.36991,"bits":-98.50909,"link":-97.68871,"sats":-98.50909},"ath_date":{"aed":"2022-04-28T21:20:31.780Z","ars":"2022-04-28T21:20:31.780Z","aud":"2022-04-28T21:20:31.780Z","bch":"2022-08-02T16:01:09.339Z","bdt":"2022-04-28T21:20:31.780Z","bhd":"2022-04-28T21:20:31.780Z","bmd":"2022-04-28T21:20:31.780Z","bnb":"2022-04-28T21:20:31.780Z","brl":"2022-04-28T21:20:31.780Z","btc":"2022-08-02T16:01:09.339Z","cad":"2022-04-28T21:20:31.780Z","chf":"2022-04-28T21:20:31.780Z","clp":"2022-04-28T21:20:31.780Z","cny":"2022-04-28T21:20:31.780Z","czk":"2022-04-28T21:20:31.780Z","dkk":"2022-04-28T21:20:31.780Z","dot":"2022-08-02T15:45:49.111Z","eos":"2022-08-02T16:01:09.339Z","eth":"2022-08-02T16:01:09.339Z","eur":"2022-04-28T21:20:31.780Z","gbp":"2022-04-28T21:20:31.780Z","hkd":"2022-04-28T21:20:31.780Z","huf":"2022-04-28T21:20:31.780Z","idr":"2022-04-28T21:20:31.780Z","ils":"2022-04-28T21:20:31.780Z","inr":"2022-04-28T21:20:31.780Z","jpy":"2022-04-28T21:20:31.780Z","krw":"2022-04-28T21:20:31.780Z","kwd":"2022-04-28T21:20:31.780Z","lkr":"2022-04-28T21:20:31.780Z","ltc":"2022-08-02T15:45:49.111Z","mmk":"2022-04-28T21:20:31.780Z","mxn":"2022-04-28T21:20:31.780Z","myr":"2022-04-28T21:20:31.780Z","ngn":"2022-04-28T21:20:31.780Z","nok":"2022-04-28T21:20:31.780Z","nzd":"2022-04-28T21:20:31.780Z","php":"2022-04-28T21:20:31.780Z","pkr":"2022-04-28T21:20:31.780Z","pln":"2022-04-28T21:20:31.780Z","rub":"2022-04-28T21:20:31.780Z","sar":"2022-04-28T21:20:31.780Z","sek":"2022-04-28T21:20:31.780Z","sgd":"2022-08-02T16:01:09.339Z","thb":"2022-04-28T21:20:31.780Z","try":"2022-04-28T21:20:31.780Z","twd":"2022-04-28T21:20:31.780Z","uah":"2022-04-28T21:20:31.780Z","usd":"2022-04-28T21:20:31.780Z","vef":"2022-04-28T21:20:31.780Z","vnd":"2022-04-28T21:20:31.780Z","xag":"2022-04-28T21:20:31.780Z","xau":"2022-04-28T21:20:31.780Z","xdr":"2022-04-28T21:20:31.780Z","xlm":"2022-08-02T16:01:09.339Z","xrp":"2022-08-02T16:01:09.339Z","yfi":"2022-06-02T03:08:35.875Z","zar":"2022-04-28T21:20:31.780Z","bits":"2022-08-02T16:01:09.339Z","link":"2022-08-02T15:45:49.111Z","sats":"2022-08-02T16:01:09.339Z"},"atl":{"aed":0.318845,"ars":22.27,"aud":0.130285,"bch":0.00027136,"bdt":9.39,"bhd":0.03269329,"bmd":0.086807,"bnb":0.0003603,"brl":0.41579,"btc":2.85e-06,"cad":0.115005,"chf":0.07767,"clp":69.57,"cny":0.629674,"czk":1.89,"dkk":0.592412,"dot":0.0167717,"eos":0.11325996,"eth":4.491e-05,"eur":0.07952,"gbp":0.068317,"hkd":0.680279,"huf":29.66,"idr":1305.61,"ils":0.322,"inr":7.13,"jpy":12.53,"krw":114.26,"kwd":0.02669151,"lkr":26.74,"ltc":0.00079895,"mmk":182.31,"mxn":1.49,"myr":0.405173,"ngn":42.6,"nok":0.932363,"nzd":0.141425,"php":4.8,"pkr":24.87,"pln":0.352792,"rub":7.64,"sar":0.325598,"sek":0.93699,"sgd":0.117381,"thb":3.06,"try":2.16,"twd":2.71,"uah":3.21,"usd":0.086807,"vef":0.00869202,"vnd":2046.7,"xag":0.00381219,"xau":4.522e-05,"xdr":0.065109,"xlm":0.77878721,"xrp":0.18000976,"yfi":1.311e-05,"zar":1.63,"bits":2.85,"link":0.01375075,"sats":284.84},"atl_change_percentage":{"aed":9.36266,"ars":9.36266,"aud":9.36266,"bch":18.68649,"bdt":9.36266,"bhd":9.36266,"bmd":9.36266,"bnb":8.14975,"brl":9.36266,"btc":8.97202,"cad":9.36266,"chf":9.36266,"clp":9.36266,"cny":9.36266,"czk":9.36266,"dkk":9.36266,"dot":6.02961,"eos":7.07126,"eth":9.7303,"eur":9.36266,"gbp":9.36266,"hkd":9.36266,"huf":9.36266,"idr":9.36266,"ils":9.36266,"inr":9.36266,"jpy":9.36266,"krw":9.36266,"kwd":9.36266,"lkr":9.36266,"ltc":11.38577,"mmk":9.36266,"mxn":9.36266,"myr":9.36266,"ngn":69.44252,"nok":9.36266,"nzd":9.36266,"php":9.36266,"pkr":9.36266,"pln":9.36266,"rub":10.39608,"sar":9.36266,"sek":9.36266,"sgd":9.36266,"thb":9.36266,"try":14.66468,"twd":9.36266,"uah":9.36266,"usd":9.36266,"vef":9.36266,"vnd":9.36266,"xag":9.36266,"xau":9.36266,"xdr":9.36266,"xlm":13.10065,"xrp":11.70026,"yfi":9.18146,"zar":9.36266,"bits":8.97202,"link":10.35243,"sats":8.97202},"atl_date":{"aed":"2023-06-30T23:25:21.073Z","ars":"2023-06-30T23:25:21.073Z","aud":"2023-06-30T23:25:21.073Z","bch":"2023-06-30T17:05:48.160Z","bdt":"2023-06-30T23:25:21.073Z","bhd":"2023-06-30T23:25:21.073Z","bmd":"2023-06-30T23:25:21.073Z","bnb":"2023-06-30T23:25:21.073Z","brl":"2023-06-30T23:25:21.073Z","btc":"2023-06-30T23:25:21.073Z","cad":"2023-06-30T23:25:21.073Z","chf":"2023-06-30T23:25:21.073Z","clp":"2023-06-30T23:25:21.073Z","cny":"2023-06-30T23:25:21.073Z","czk":"2023-06-30T23:25:21.073Z","dkk":"2023-06-30T23:25:21.073Z","dot":"2023-06-30T23:25:21.073Z","eos":"2023-07-01T01:05:28.142Z","eth":"2023-06-30T23:25:21.073Z","eur":"2023-06-30T23:25:21.073Z","gbp":"2023-06-30T23:25:21.073Z","hkd":"2023-06-30T23:25:21.073Z","huf":"2023-06-30T23:25:21.073Z","idr":"2023-06-30T23:25:21.073Z","ils":"2023-06-30T23:25:21.073Z","inr":"2023-06-30T23:25:21.073Z","jpy":"2023-06-30T23:25:21.073Z","krw":"2023-06-30T23:25:21.073Z","kwd":"2023-06-30T23:25:21.073Z","lkr":"2023-06-30T23:25:21.073Z","ltc":"2023-06-30T17:26:03.340Z","mmk":"2023-06-30T23:25:21.073Z","mxn":"2023-06-30T23:25:21.073Z","myr":"2023-06-30T23:25:21.073Z","ngn":"2023-06-15T04:34:26.246Z","nok":"2023-06-30T23:25:21.073Z","nzd":"2023-06-30T23:25:21.073Z","php":"2023-06-30T23:25:21.073Z","pkr":"2023-06-30T23:25:21.073Z","pln":"2023-06-30T23:25:21.073Z","rub":"2023-06-29T01:00:35.949Z","sar":"2023-06-30T23:25:21.073Z","sek":"2023-06-30T23:25:21.073Z","sgd":"2023-06-30T23:25:21.073Z","thb":"2023-06-30T23:25:21.073Z","try":"2023-06-15T04:34:26.246Z","twd":"2023-06-30T23:25:21.073Z","uah":"2023-06-30T23:25:21.073Z","usd":"2023-06-30T23:25:21.073Z","vef":"2023-06-30T23:25:21.073Z","vnd":"2023-06-30T23:25:21.073Z","xag":"2023-06-30T23:25:21.073Z","xau":"2023-06-30T23:25:21.073Z","xdr":"2023-06-30T23:25:21.073Z","xlm":"2023-06-30T18:25:41.792Z","xrp":"2023-06-13T11:51:07.139Z","yfi":"2023-06-30T21:35:32.230Z","zar":"2023-06-30T23:25:21.073Z","bits":"2023-06-30T23:25:21.073Z","link":"2023-06-30T23:25:21.073Z","sats":"2023-06-30T23:25:21.073Z"},"market_cap":{"aed":185124803,"ars":12927987617,"aud":75644615,"bch":171136,"bdt":5452704692,"bhd":18982043,"bmd":50401182,"bnb":206851,"brl":241411584,"btc":1648,"cad":66772999,"chf":45095904,"clp":40395035691,"cny":365595057,"czk":1097515988,"dkk":343960350,"dot":9447814,"eos":64344426,"eth":26159,"eur":46170003,"gbp":39665680,"hkd":394976426,"huf":17222084040,"idr":758048904261,"ils":186956130,"inr":4137747973,"jpy":7274651032,"krw":66343115407,"kwd":15497356,"lkr":15525278185,"ltc":471886,"mmk":105848885083,"mxn":863084968,"myr":235247519,"ngn":38318506974,"nok":541338940,"nzd":82112800,"php":2785874908,"pkr":14439938769,"pln":204834236,"rub":4476935784,"sar":189045108,"sek":544025323,"sgd":68152479,"thb":1775380291,"try":1313006244,"twd":1570566366,"uah":1861545497,"usd":50401182,"vef":5046670,"vnd":1188333878993,"xag":2213394,"xau":26257,"xdr":37802752,"xlm":468112161,"xrp":106788060,"yfi":7612,"zar":948568146,"bits":1648038412,"link":8065206,"sats":164803841199},"market_cap_rank":398,"fully_diluted_valuation":{"aed":349658341,"ars":24418006792,"aud":142875347,"bch":323237,"bdt":10298909943,"bhd":35852730,"bmd":95196287,"bnb":390694,"brl":455971174,"btc":3113,"cad":126118896,"chf":85175830,"clp":76296967869,"cny":690525305,"czk":2072956260,"dkk":649662298,"dot":17844757,"eos":121531879,"eth":49409,"eur":87204558,"gbp":74919382,"hkd":746019980,"huf":32528571152,"idr":1431780710249,"ils":353117298,"inr":7815257958,"jpy":13740149169,"krw":125306945717,"kwd":29270954,"lkr":29323693631,"ltc":891284,"mmk":199924293818,"mxn":1630169772,"myr":444328668,"ngn":72374880859,"nok":1022465236,"nzd":155092267,"php":5261879454,"pkr":27273736128,"pln":386884944,"rub":8455906025,"sar":357062898,"sek":1027539199,"sgd":128724419,"thb":3353286627,"try":2479967983,"twd":2966440047,"uah":3516032961,"usd":95196287,"vef":9532004,"vnd":2244490448721,"xag":4180594,"xau":49593,"xdr":71400737,"xlm":884156627,"xrp":201698181,"yfi":14378,"zar":1791627910,"bits":3112766993,"link":15233327,"sats":311276699270},"total_volume":{"aed":2636587,"ars":184123134,"aud":1077347,"bch":2443,"bdt":77658573,"bhd":270346,"bmd":717824,"bnb":2948,"brl":3438235,"btc":23.471844,"cad":950995,"chf":642265,"clp":575314641,"cny":5206882,"czk":15631055,"dkk":4898756,"dot":134399,"eos":917033,"eth":372.883,"eur":657563,"gbp":564927,"hkd":5625338,"huf":245280563,"idr":10796292810,"ils":2662669,"inr":58930682,"jpy":103607118,"krw":944872680,"kwd":220717,"lkr":221114295,"ltc":6742,"mmk":1507522207,"mxn":12292239,"myr":3350445,"ngn":545740280,"nok":7709864,"nzd":1169468,"php":39677020,"pkr":205656662,"pln":2917293,"rub":63761466,"sar":2692420,"sek":7748124,"sgd":970642,"thb":25285342,"try":18700113,"twd":22368338,"uah":26512525,"usd":717824,"vef":71876,"vnd":16924502419,"xag":31524,"xau":373.96,"xdr":538395,"xlm":6662720,"xrp":1520128,"yfi":108.224,"zar":13509708,"bits":23471844,"link":114814,"sats":2347184354},"high_24h":{"aed":0.353695,"ars":24.7,"aud":0.144525,"bch":0.00032932,"bdt":10.42,"bhd":0.03626664,"bmd":0.096295,"bnb":0.00039612,"brl":0.461235,"btc":3.16e-06,"cad":0.127575,"chf":0.086159,"clp":77.18,"cny":0.698497,"czk":2.1,"dkk":0.657162,"dot":0.01868301,"eos":0.13144417,"eth":5.005e-05,"eur":0.088211,"gbp":0.075784,"hkd":0.754633,"huf":32.9,"idr":1448.31,"ils":0.357194,"inr":7.91,"jpy":13.9,"krw":126.75,"kwd":0.02960888,"lkr":29.66,"ltc":0.00098794,"mmk":202.23,"mxn":1.65,"myr":0.449458,"ngn":73.21,"nok":1.034,"nzd":0.156883,"php":5.32,"pkr":27.59,"pln":0.391351,"rub":8.55,"sar":0.361185,"sek":1.039,"sgd":0.13021,"thb":3.39,"try":2.51,"twd":3.0,"uah":3.56,"usd":0.096295,"vef":0.00964205,"vnd":2270.4,"xag":0.00422886,"xau":5.017e-05,"xdr":0.072225,"xlm":0.89826678,"xrp":0.2042618,"yfi":1.468e-05,"zar":1.81,"bits":3.16,"link":0.01550574,"sats":315.52},"low_24h":{"aed":0.318845,"ars":22.27,"aud":0.130285,"bch":0.00027136,"bdt":9.39,"bhd":0.03269329,"bmd":0.086807,"bnb":0.0003603,"brl":0.41579,"btc":2.85e-06,"cad":0.115005,"chf":0.07767,"clp":69.57,"cny":0.629674,"czk":1.89,"dkk":0.592412,"dot":0.0167717,"eos":0.11325996,"eth":4.491e-05,"eur":0.07952,"gbp":0.068317,"hkd":0.680279,"huf":29.66,"idr":1305.61,"ils":0.322,"inr":7.13,"jpy":12.53,"krw":114.26,"kwd":0.02669151,"lkr":26.74,"ltc":0.00079895,"mmk":182.31,"mxn":1.49,"myr":0.405173,"ngn":66.0,"nok":0.932363,"nzd":0.141425,"php":4.8,"pkr":24.87,"pln":0.352792,"rub":7.71,"sar":0.325598,"sek":0.93699,"sgd":0.117381,"thb":3.06,"try":2.26,"twd":2.71,"uah":3.21,"usd":0.086807,"vef":0.00869202,"vnd":2046.7,"xag":0.00381219,"xau":4.522e-05,"xdr":0.065109,"xlm":0.77878721,"xrp":0.18229446,"yfi":1.311e-05,"zar":1.63,"bits":2.85,"link":0.01375075,"sats":284.84},"price_change_24h":0.00127799,"price_change_percentage_24h":1.36365,"price_change_percentage_7d":-3.9846,"price_change_percentage_14d":-6.36516,"price_change_percentage_30d":-28.78983,"price_change_percentage_60d":-67.16647,"price_change_percentage_200d":-76.14133,"price_change_percentage_1y":-95.14363,"market_cap_change_24h":697525,"market_cap_change_percentage_24h":1.40337,"price_change_24h_in_currency":{"aed":0.00469126,"ars":0.354616,"aud":0.001191,"bch":2.199e-05,"bdt":0.13826,"bhd":0.00044401,"bmd":0.00127799,"bnb":1.21e-06,"brl":0.00137916,"btc":8.8056e-08,"cad":0.00150296,"chf":0.00066335,"clp":0.927737,"cny":0.00810802,"czk":0.02004411,"dkk":0.00635235,"dot":-0.000287172075208283,"eos":-0.002297014836707967,"eth":-3.615850326e-09,"eur":0.00081888,"gbp":0.00072865,"hkd":0.01002449,"huf":0.384437,"idr":15.27,"ils":0.00303015,"inr":0.105461,"jpy":0.157554,"krw":1.23,"kwd":0.00038967,"lkr":0.393663,"ltc":-2.7401913566872e-05,"mmk":2.68,"mxn":0.02560408,"myr":0.005965,"ngn":0.522704,"nok":0.01028556,"nzd":0.00078717,"php":0.069702,"pkr":0.358968,"pln":0.00333652,"rub":0.115023,"sar":0.0048066,"sek":0.0075576,"sgd":0.00142922,"thb":0.02552111,"try":0.03148472,"twd":0.03980512,"uah":0.04720182,"usd":0.00127799,"vef":0.00012796,"vnd":29.44,"xag":-6.539303215844e-06,"xau":3.24646e-07,"xdr":0.00095854,"xlm":0.05408726,"xrp":0.00677069,"yfi":2.25065e-07,"zar":0.01506158,"bits":0.088056,"link":0.0001925,"sats":8.81},"price_change_percentage_1h_in_currency":{"aed":-0.62741,"ars":-0.62741,"aud":-0.62741,"bch":-1.24316,"bdt":-0.62741,"bhd":-0.62741,"bmd":-0.62741,"bnb":-0.90598,"brl":-0.62741,"btc":-0.93715,"cad":-0.62741,"chf":-0.62741,"clp":-0.62741,"cny":-0.62741,"czk":-0.62741,"dkk":-0.62741,"dot":-1.79795,"eos":-0.9984,"eth":-0.76177,"eur":-0.62741,"gbp":-0.62741,"hkd":-0.62741,"huf":-0.62741,"idr":-0.62741,"ils":-0.62741,"inr":-0.62741,"jpy":-0.62741,"krw":-0.62741,"kwd":-0.62741,"lkr":-0.62741,"ltc":-0.97448,"mmk":-0.62741,"mxn":-0.62741,"myr":-0.62741,"ngn":-0.62741,"nok":-0.62741,"nzd":-0.62741,"php":-0.62741,"pkr":-0.62741,"pln":-0.62741,"rub":-0.62741,"sar":-0.62741,"sek":-0.62741,"sgd":-0.62741,"thb":-0.62741,"try":-0.62741,"twd":-0.62741,"uah":-0.62741,"usd":-0.62741,"vef":-0.62741,"vnd":-0.62741,"xag":-0.62741,"xau":-0.62741,"xdr":-0.62741,"xlm":-1.49449,"xrp":-0.91801,"yfi":-1.60521,"zar":-0.62741,"bits":-0.93715,"link":-1.52772,"sats":-0.93715},"price_change_percentage_24h_in_currency":{"aed":1.36282,"ars":1.47682,"aud":0.84239,"bch":7.29509,"bdt":1.36365,"bhd":1.25664,"bmd":1.36365,"bnb":0.31144,"brl":0.30403,"btc":2.91752,"cad":1.20865,"chf":0.78658,"clp":1.23355,"cny":1.19067,"czk":0.97845,"dkk":0.98955,"dot":-1.58893,"eos":-1.85758,"eth":-0.00733,"eur":0.94995,"gbp":0.98422,"hkd":1.36494,"huf":1.19853,"idr":1.08035,"ils":0.86738,"inr":1.37081,"jpy":1.16244,"krw":0.99611,"kwd":1.35211,"lkr":1.36365,"ltc":-2.97954,"mmk":1.36365,"mxn":1.59912,"myr":1.36365,"ngn":0.72902,"nok":1.01834,"nzd":0.51122,"php":1.34532,"pkr":1.33657,"pln":0.87176,"rub":1.38198,"sar":1.36743,"sek":0.74253,"sgd":1.12516,"thb":0.76854,"try":1.28863,"twd":1.36301,"uah":1.36365,"usd":1.36365,"vef":1.36365,"vnd":1.3318,"xag":-0.1565,"xau":0.66033,"xdr":1.36365,"xlm":6.53505,"xrp":3.48284,"yfi":1.59653,"zar":0.84959,"bits":2.91752,"link":1.28321,"sats":2.91752},"price_change_percentage_7d_in_currency":{"aed":-3.98394,"ars":-2.26762,"aud":-3.74872,"bch":-37.34204,"bdt":-3.98275,"bhd":-4.06764,"bmd":-3.9846,"bnb":-3.31886,"brl":-3.84843,"btc":-3.63325,"cad":-3.68741,"chf":-4.18912,"clp":-4.23313,"cny":-2.99768,"czk":-3.68915,"dkk":-4.14121,"dot":-9.1721,"eos":-10.28944,"eth":-5.6298,"eur":-3.9846,"gbp":-3.92796,"hkd":-3.90612,"huf":-3.44673,"idr":-4.01651,"ils":-1.85912,"inr":-3.8224,"jpy":-3.557,"krw":-3.4133,"kwd":-3.9771,"lkr":-3.98204,"ltc":-17.98154,"mmk":-3.98158,"mxn":-4.20054,"myr":-4.16938,"ngn":-11.303,"nok":-4.73233,"nzd":-3.91489,"php":-4.683,"pkr":-3.9846,"pln":-4.21188,"rub":0.80882,"sar":-3.99271,"sek":-3.31561,"sgd":-3.97039,"thb":-3.6613,"try":-0.99324,"twd":-3.4959,"uah":-3.97852,"usd":-3.9846,"vef":-3.9846,"vnd":-3.76575,"xag":-5.45196,"xau":-3.90528,"xdr":-3.43847,"xlm":-18.8685,"xrp":0.25805,"yfi":-4.84837,"zar":-3.58771,"bits":-3.63325,"link":-5.62736,"sats":-3.63325},"price_change_percentage_14d_in_currency":{"aed":-6.36223,"ars":-3.38378,"aud":-3.44108,"bch":-65.93238,"bdt":-6.33954,"bhd":-6.18756,"bmd":-6.36516,"bnb":-5.64846,"brl":-6.98368,"btc":-18.79989,"cad":-6.01898,"chf":-6.24969,"clp":-5.43421,"cny":-4.69121,"czk":-6.01209,"dkk":-6.13891,"dot":-20.54221,"eos":-23.6249,"eth":-15.39111,"eur":-6.02148,"gbp":-5.49928,"hkd":-6.17779,"huf":-6.28562,"idr":-5.87168,"ils":-2.36691,"inr":-6.14853,"jpy":-4.7148,"krw":-3.50614,"kwd":-6.17597,"lkr":-6.87956,"ltc":-32.17169,"mmk":-6.28047,"mxn":-6.12285,"myr":-5.28971,"ngn":8.43528,"nok":-4.82147,"nzd":-5.20647,"php":-7.20624,"pkr":-6.6665,"pln":-6.78254,"rub":-0.85887,"sar":-6.32932,"sek":-5.12226,"sgd":-5.54086,"thb":-4.58173,"try":3.2705,"twd":-4.84103,"uah":-6.27305,"usd":-6.36516,"vef":-6.36516,"vnd":-6.17381,"xag":-0.49318,"xau":-4.49712,"xdr":-6.28207,"xlm":-31.64371,"xrp":-4.74014,"yfi":-18.64056,"zar":-3.1131,"bits":-18.79989,"link":-19.84009,"sats":-18.79989},"price_change_percentage_30d_in_currency":{"aed":-28.78828,"ars":-23.69138,"aud":-30.29021,"bch":-72.61635,"bdt":-28.15742,"bhd":-28.86369,"bmd":-28.78983,"bnb":-10.90284,"brl":-32.54174,"btc":-37.40679,"cad":-30.4458,"chf":-29.83787,"clp":-29.47444,"cny":-27.35674,"czk":-29.91217,"dkk":-30.13156,"dot":-30.28452,"eos":-19.34775,"eth":-31.16242,"eur":-30.15644,"gbp":-30.10261,"hkd":-28.75379,"huf":-29.65028,"idr":-28.244,"ils":-29.08244,"inr":-29.08827,"jpy":-26.30563,"krw":-29.02276,"kwd":-28.80303,"lkr":-25.61649,"ltc":-38.28686,"mmk":-28.75577,"mxn":-30.80113,"myr":-27.95633,"ngn":17.45612,"nok":-31.47808,"nzd":-30.12158,"php":-29.90204,"pkr":-28.46161,"pln":-31.82069,"rub":-22.00887,"sar":-28.78858,"sek":-29.28843,"sgd":-28.76059,"thb":-27.80878,"try":-10.79732,"twd":-27.77981,"uah":-28.75908,"usd":-28.78983,"vef":-28.78983,"vnd":-28.51838,"xag":-26.47878,"xau":-27.0148,"xdr":-28.85017,"xlm":-38.73891,"xrp":-23.76307,"yfi":-31.03343,"zar":-32.14734,"bits":-37.40679,"link":-27.09434,"sats":-37.40679},"price_change_percentage_60d_in_currency":{"aed":-67.16536,"ars":-62.16206,"aud":-66.9616,"bch":-86.67566,"bdt":-66.4778,"bhd":-67.20583,"bmd":-67.16647,"bnb":-56.18318,"brl":-68.47808,"btc":-69.8901,"cad":-67.95085,"chf":-67.25464,"clp":-67.37125,"cny":-65.54382,"czk":-66.76795,"dkk":-67.03422,"dot":-65.16458,"eos":-57.2916,"eth":-68.75244,"eur":-67.01589,"gbp":-67.75657,"hkd":-67.22208,"huf":-66.89922,"idr":-66.46891,"ils":-66.37381,"inr":-67.06751,"jpy":-65.4911,"krw":-67.7715,"kwd":-67.06901,"lkr":-68.05538,"ltc":-72.80523,"mmk":-67.11597,"mxn":-68.68868,"myr":-65.66969,"ngn":-45.71805,"nok":-67.07236,"nzd":-66.74379,"php":-67.22488,"pkr":-66.81722,"pln":-68.02984,"rub":-63.43442,"sar":-67.15931,"sek":-65.54316,"sgd":-66.75881,"thb":-66.14286,"try":-56.07229,"twd":-66.78326,"uah":-66.95459,"usd":-67.16647,"vef":-67.16647,"vnd":-67.00906,"xag":-64.28195,"xau":-65.98398,"xdr":-66.76259,"xlm":-71.85083,"xrp":-67.95448,"yfi":-60.51958,"zar":-66.33515,"bits":-69.8901,"link":-63.83755,"sats":-69.8901},"price_change_percentage_200d_in_currency":{"aed":-76.14068,"ars":-64.27162,"aud":-75.76322,"bch":-91.18919,"bdt":-74.99537,"bhd":-76.16285,"bmd":-76.14133,"bnb":-73.70903,"brl":-78.53123,"btc":-86.39269,"cad":-76.79969,"chf":-77.22047,"clp":-77.93062,"cny":-75.20827,"czk":-77.45144,"dkk":-76.92689,"dot":-76.98171,"eos":-70.10513,"eth":-84.04516,"eur":-76.96134,"gbp":-76.91138,"hkd":-75.97084,"huf":-79.04062,"idr":-77.10874,"ils":-74.22203,"inr":-76.35169,"jpy":-74.9699,"krw":-75.9915,"kwd":-76.09211,"lkr":-80.04965,"ltc":-82.78447,"mmk":-76.19683,"mxn":-79.41312,"myr":-74.85655,"ngn":-59.2252,"nok":-74.182,"nzd":-75.12906,"php":-76.35882,"pkr":-69.67932,"pln":-78.23273,"rub":-66.47519,"sar":-76.18783,"sek":-75.04479,"sgd":-76.19945,"thb":-75.86523,"try":-66.66792,"twd":-75.77848,"uah":-76.19918,"usd":-76.14133,"vef":-76.14133,"vnd":-76.19104,"xag":-75.46136,"xau":-77.77882,"xdr":-76.27409,"xlm":-81.6011,"xrp":-80.48457,"yfi":-76.88917,"zar":-74.55573,"bits":-86.39269,"link":-74.35053,"sats":-86.39269},"price_change_percentage_1y_in_currency":{"aed":-95.14373,"ars":-90.05189,"aud":-95.05692,"bch":-98.35266,"bdt":-94.37786,"bhd":-95.14841,"bmd":-95.14363,"bnb":-95.63728,"brl":-95.57228,"btc":-96.95218,"cad":-95.02531,"chf":-95.47785,"clp":-95.76042,"cny":-94.74371,"czk":-95.54022,"dkk":-95.35021,"dot":-93.91,"eos":-94.40258,"eth":-97.35489,"eur":-95.35677,"gbp":-95.39947,"hkd":-95.15001,"huf":-95.68477,"idr":-95.12253,"ils":-94.88155,"inr":-94.95426,"jpy":-94.81839,"krw":-95.07173,"kwd":-95.13336,"lkr":-95.84356,"ltc":-97.68599,"mmk":-94.49005,"mxn":-95.89529,"myr":-94.85657,"ngn":-91.101,"nok":-94.746,"nzd":-95.12494,"php":-95.13015,"pkr":-93.19871,"pln":-95.63568,"rub":-92.18147,"sar":-95.14602,"sek":-94.92437,"sgd":-95.29478,"thb":-95.20404,"try":-92.44681,"twd":-94.92528,"uah":-93.92788,"usd":-95.14363,"vef":-95.14363,"vnd":-95.08759,"xag":-95.81566,"xau":-95.47815,"xdr":-94.99979,"xlm":-95.0779,"xrp":-96.76899,"yfi":-96.136,"zar":-94.43089,"bits":-96.95218,"link":-95.33821,"sats":-96.95218},"market_cap_change_24h_in_currency":{"aed":2561776,"ars":192548573,"aud":675345,"bch":10880,"bdt":75462419,"bhd":246398,"bmd":697525,"bnb":812.502,"brl":537717,"btc":46.344165,"cad":842438,"chf":340245,"clp":481507256,"cny":4418456,"czk":12316143,"dkk":3443869,"dot":-159503.235101223,"eos":-1184207.131885536,"eth":-58.6777129259026,"eur":448354,"gbp":416888,"hkd":5434793,"huf":219904065,"idr":8687120683,"ils":1820641,"inr":58054532,"jpy":88098538,"krw":667092155,"kwd":208809,"lkr":214861267,"ltc":-18355.532472106453,"mmk":1464890054,"mxn":14166969,"myr":3255696,"ngn":292226432,"nok":6110070,"nzd":488558,"php":38132239,"pkr":196035507,"pln":1884459,"rub":52853302,"sar":2625077,"sek":4165712,"sgd":778823,"thb":14876726,"try":17787817,"twd":21853767,"uah":25762761,"usd":697525,"vef":69843,"vnd":16077534707,"xag":-1075.3032958442345,"xau":173.51,"xdr":523169,"xlm":28620896,"xrp":3522206,"yfi":115.679,"zar":8558352,"bits":46344165,"link":88538,"sats":4634416548},"market_cap_change_percentage_24h_in_currency":{"aed":1.40323,"ars":1.51191,"aud":0.90083,"bch":6.78934,"bdt":1.40337,"bhd":1.31513,"bmd":1.40337,"bnb":0.39435,"brl":0.22324,"btc":2.89345,"cad":1.27777,"chf":0.76023,"clp":1.20638,"cny":1.22335,"czk":1.13492,"dkk":1.01137,"dot":-1.66023,"eos":-1.80716,"eth":-0.22381,"eur":0.98062,"gbp":1.06217,"hkd":1.39518,"huf":1.29339,"idr":1.15927,"ils":0.98341,"inr":1.42301,"jpy":1.22588,"krw":1.01573,"kwd":1.36578,"lkr":1.40337,"ltc":-3.74418,"mmk":1.40337,"mxn":1.66883,"myr":1.40337,"ngn":0.76849,"nok":1.14158,"nzd":0.59855,"php":1.38777,"pkr":1.37628,"pln":0.92853,"rub":1.19467,"sar":1.40815,"sek":0.77163,"sgd":1.15598,"thb":0.84503,"try":1.37334,"twd":1.41109,"uah":1.40337,"usd":1.40337,"vef":1.40337,"vnd":1.3715,"xag":-0.04856,"xau":0.66523,"xdr":1.40337,"xlm":6.51228,"xrp":3.41081,"yfi":1.54306,"zar":0.91045,"bits":2.89345,"link":1.10997,"sats":2.89345},"total_supply":1000000000.0,"max_supply":null,"circulating_supply":529444836.653465,"last_updated":"2023-07-01T12:28:54.894Z"},"public_interest_stats":{"alexa_rank":null,"bing_matches":null},"status_updates":[],"last_updated":"2023-07-01T12:28:54.894Z","tickers":[{"base":"IBC/6AE98883D4D5D5FF9E50D7130F1305DA2FFA0C652D1DD9C123657C6B4EB2DF8A","target":"UOSMO","market":{"name":"Osmosis","identifier":"osmosis","has_trading_incentive":false},"last":0.190218478978219,"volume":2377801.690586003,"converted_last":{"btc":3.08e-06,"eth":4.895e-05,"usd":0.094224},"converted_volume":{"btc":7.32597,"eth":116.383,"usd":224045},"trust_score":"green","bid_ask_spread_percentage":0.603135,"timestamp":"2023-07-01T12:24:26+00:00","last_traded_at":"2023-07-01T12:24:26+00:00","last_fetch_at":"2023-07-01T12:28:13+00:00","is_anomaly":false,"is_stale":false,"trade_url":"https://app.osmosis.zone/?from=ibc/6AE98883D4D5D5FF9E50D7130F1305DA2FFA0C652D1DD9C123657C6B4EB2DF8A\u0026to=uosmo","token_info_url":null,"coin_id":"evmos","target_coin_id":"osmosis"},{"base":"EVMOS","target":"ETH","market":{"name":"DigiFinex","identifier":"digifinex","has_trading_incentive":false},"last":4.97e-05,"volume":1878295.5518,"converted_last":{"btc":3.13e-06,"eth":4.967e-05,"usd":0.095664},"converted_volume":{"btc":5.874597,"eth":93.3,"usd":179685},"trust_score":"green","bid_ask_spread_percentage":0.400802,"timestamp":"2023-07-01T12:26:33+00:00","last_traded_at":"2023-07-01T12:26:33+00:00","last_fetch_at":"2023-07-01T12:26:33+00:00","is_anomaly":false,"is_stale":false,"trade_url":"https://www.digifinex.com/en-ww/trade/ETH/EVMOS","token_info_url":null,"coin_id":"evmos","target_coin_id":"ethereum"},{"base":"EVMOS","target":"USDT","market":{"name":"Bitget","identifier":"bitget","has_trading_incentive":false},"last":0.09414,"volume":661965.7801,"converted_last":{"btc":3.08e-06,"eth":4.888e-05,"usd":0.094112},"converted_volume":{"btc":1.964314,"eth":31.203579,"usd":60083},"trust_score":"green","bid_ask_spread_percentage":0.560017,"timestamp":"2023-07-01T12:27:31+00:00","last_traded_at":"2023-07-01T12:27:31+00:00","last_fetch_at":"2023-07-01T12:27:31+00:00","is_anomaly":false,"is_stale":false,"trade_url":"https://www.bitget.com/en/spot/EVMOSUSDT_SPBL","token_info_url":null,"coin_id":"evmos","target_coin_id":"tether"},{"base":"EVMOS","target":"BTC","market":{"name":"DigiFinex","identifier":"digifinex","has_trading_incentive":false},"last":3.13e-06,"volume":1379850.16,"converted_last":{"btc":3.13e-06,"eth":4.971e-05,"usd":0.095736},"converted_volume":{"btc":4.318931,"eth":68.593,"usd":132102},"trust_score":"green","bid_ask_spread_percentage":0.318471,"timestamp":"2023-07-01T12:26:33+00:00","last_traded_at":"2023-07-01T12:26:33+00:00","last_fetch_at":"2023-07-01T12:26:33+00:00","is_anomaly":false,"is_stale":false,"trade_url":"https://www.digifinex.com/en-ww/trade/BTC/EVMOS","token_info_url":null,"coin_id":"evmos","target_coin_id":"bitcoin"},{"base":"0X15C3EB3B621D1BFF62CBA1C9536B7C1AE9149B57","target":"0XD4949664CD82660AAE99BEDC034A0DEA8A0BD517","market":{"name":"SpaceFi","identifier":"spacefi","has_trading_incentive":false},"last":10.6546625083754,"volume":28082.739675,"converted_last":{"btc":3.11e-06,"eth":4.934e-05,"usd":0.095019},"converted_volume":{"btc":0.95345001,"eth":15.139494,"usd":29158},"trust_score":"green","bid_ask_spread_percentage":0.614031,"timestamp":"2023-07-01T11:23:52+00:00","last_traded_at":"2023-07-01T11:23:52+00:00","last_fetch_at":"2023-07-01T12:25:40+00:00","is_anomaly":false,"is_stale":false,"trade_url":"https://swap-evmos.spacefi.io/#/swap?inputCurrency=0x15c3eb3b621d1bff62cba1c9536b7c1ae9149b57\u0026outputCurrency=0xd4949664cd82660aae99bedc034a0dea8a0bd517","token_info_url":null,"coin_id":"axlusdc","target_coin_id":"evmos"},{"base":"0X4E2D4F33D759976381D9DEE04B197BF52F6BC1FC","target":"0XD4949664CD82660AAE99BEDC034A0DEA8A0BD517","market":{"name":"SpaceFi","identifier":"spacefi","has_trading_incentive":false},"last":0.116525705909834,"volume":33500.42851586996,"converted_last":{"btc":3.11e-06,"eth":4.934e-05,"usd":0.095019},"converted_volume":{"btc":0.01243194,"eth":0.19740243,"usd":380.18},"trust_score":"green","bid_ask_spread_percentage":0.616729,"timestamp":"2023-07-01T12:21:49+00:00","last_traded_at":"2023-07-01T12:21:49+00:00","last_fetch_at":"2023-07-01T12:25:40+00:00","is_anomaly":false,"is_stale":false,"trade_url":"https://swap-evmos.spacefi.io/#/swap?inputCurrency=0x4e2d4f33d759976381d9dee04b197bf52f6bc1fc\u0026outputCurrency=0xd4949664cd82660aae99bedc034a0dea8a0bd517","token_info_url":null,"coin_id":"spacefi","target_coin_id":"evmos"},{"base":"EVMOS","target":"USDT","market":{"name":"DigiFinex","identifier":"digifinex","has_trading_incentive":false},"last":0.09574,"volume":182902.5111,"converted_last":{"btc":3.13e-06,"eth":4.97e-05,"usd":0.095709},"converted_volume":{"btc":0.57232188,"eth":9.089555,"usd":17505.45},"trust_score":"green","bid_ask_spread_percentage":0.343857,"timestamp":"2023-07-01T12:26:33+00:00","last_traded_at":"2023-07-01T12:26:33+00:00","last_fetch_at":"2023-07-01T12:26:33+00:00","is_anomaly":false,"is_stale":false,"trade_url":"https://www.digifinex.com/en-ww/trade/USDT/EVMOS","token_info_url":null,"coin_id":"evmos","target_coin_id":"tether"},{"base":"EVMOS","target":"USDT","market":{"name":"Huobi","identifier":"huobi","has_trading_incentive":false},"last":0.0949,"volume":256783.50142729346,"converted_last":{"btc":3.1e-06,"eth":4.926e-05,"usd":0.094869},"converted_volume":{"btc":0.76777265,"eth":12.193684,"usd":23484},"trust_score":"green","bid_ask_spread_percentage":2.21519,"timestamp":"2023-07-01T11:58:17+00:00","last_traded_at":"2023-07-01T11:58:17+00:00","last_fetch_at":"2023-07-01T12:26:13+00:00","is_anomaly":false,"is_stale":false,"trade_url":"https://www.huobi.com/en-us/exchange/evmos_usdt","token_info_url":null,"coin_id":"evmos","target_coin_id":"tether"},{"base":"IBC/1DC495FCEFDA068A3820F903EDBD78B942FBD204D7E93D3BA2B432E9669D1A59","target":"IBC/6AE98883D4D5D5FF9E50D7130F1305DA2FFA0C652D1DD9C123657C6B4EB2DF8A","market":{"name":"Osmosis","identifier":"osmosis","has_trading_incentive":false},"last":0.08987448040192586,"volume":63578.49763148819,"converted_last":{"btc":3.09e-06,"eth":4.907e-05,"usd":0.094455},"converted_volume":{"btc":0.01764822,"eth":0.28036638,"usd":539.72},"trust_score":"green","bid_ask_spread_percentage":0.629289,"timestamp":"2023-07-01T12:24:26+00:00","last_traded_at":"2023-07-01T12:24:26+00:00","last_fetch_at":"2023-07-01T12:28:13+00:00","is_anomaly":false,"is_stale":false,"trade_url":"https://app.osmosis.zone/?from=ibc/1DC495FCEFDA068A3820F903EDBD78B942FBD204D7E93D3BA2B432E9669D1A59\u0026to=ibc/6AE98883D4D5D5FF9E50D7130F1305DA2FFA0C652D1DD9C123657C6B4EB2DF8A","token_info_url":null,"coin_id":"e-money","target_coin_id":"evmos"},{"base":"EVMOS","target":"USDT","market":{"name":"MEXC","identifier":"mxc","has_trading_incentive":false},"last":0.09475,"volume":572845.8,"converted_last":{"btc":3.1e-06,"eth":4.92e-05,"usd":0.094706},"converted_volume":{"btc":1.773962,"eth":28.181836,"usd":54252},"trust_score":"green","bid_ask_spread_percentage":2.025898,"timestamp":"2023-07-01T12:28:21+00:00","last_traded_at":"2023-07-01T12:28:21+00:00","last_fetch_at":"2023-07-01T12:28:21+00:00","is_anomaly":false,"is_stale":false,"trade_url":"https://www.mexc.com/exchange/EVMOS_USDT","token_info_url":null,"coin_id":"evmos","target_coin_id":"tether"},{"base":"EVMOS","target":"BTC","market":{"name":"CoinEx","identifier":"coinex","has_trading_incentive":false},"last":3.1075e-06,"volume":79601.09089549,"converted_last":{"btc":3.11e-06,"eth":4.935e-05,"usd":0.095048},"converted_volume":{"btc":0.23658258,"eth":3.757379,"usd":7236.29},"trust_score":"green","bid_ask_spread_percentage":0.638701,"timestamp":"2023-07-01T12:26:28+00:00","last_traded_at":"2023-07-01T12:26:28+00:00","last_fetch_at":"2023-07-01T12:26:28+00:00","is_anomaly":false,"is_stale":false,"trade_url":"https://www.coinex.com/trading?currency=BTC\u0026dest=EVMOS#limit","token_info_url":null,"coin_id":"evmos","target_coin_id":"bitcoin"},{"base":"0XFA3C22C069B9556A4B2F7ECE1EE3B467909F4864","target":"0XD4949664CD82660AAE99BEDC034A0DEA8A0BD517","market":{"name":"SpaceFi","identifier":"spacefi","has_trading_incentive":false},"last":5.32797006582129,"volume":446.142458,"converted_last":{"btc":3.11e-06,"eth":4.934e-05,"usd":0.095019},"converted_volume":{"btc":0.00741644,"eth":0.11776298,"usd":226.8},"trust_score":"green","bid_ask_spread_percentage":0.702167,"timestamp":"2023-07-01T12:07:48+00:00","last_traded_at":"2023-07-01T12:07:48+00:00","last_fetch_at":"2023-07-01T12:25:39+00:00","is_anomaly":false,"is_stale":false,"trade_url":"https://swap-evmos.spacefi.io/#/swap?inputCurrency=0xfa3c22c069b9556a4b2f7ece1ee3b467909f4864\u0026outputCurrency=0xd4949664cd82660aae99bedc034a0dea8a0bd517","token_info_url":null,"coin_id":"osmosis","target_coin_id":"evmos"},{"base":"0XD4949664CD82660AAE99BEDC034A0DEA8A0BD517","target":"0XE46910336479F254723710D57E7B683F3315B22B","market":{"name":"Diffusion Finance","identifier":"diffusion","has_trading_incentive":false},"last":0.0921251901233484,"volume":327.1121604137406,"converted_last":{"btc":3.11e-06,"eth":4.933e-05,"usd":0.095032},"converted_volume":{"btc":0.00101128,"eth":0.01605637,"usd":30.93},"trust_score":"green","bid_ask_spread_percentage":0.74212,"timestamp":"2023-07-01T12:11:17+00:00","last_traded_at":"2023-07-01T12:11:17+00:00","last_fetch_at":"2023-07-01T12:24:46+00:00","is_anomaly":false,"is_stale":false,"trade_url":"https://app.diffusion.fi/#/swap?inputCurrency=0xd4949664cd82660aae99bedc034a0dea8a0bd517\u0026outputCurrency=0xe46910336479f254723710d57e7b683f3315b22b","token_info_url":null,"coin_id":"evmos","target_coin_id":"usd-coin-celer"},{"base":"EVMOS","target":"USDT","market":{"name":"CoinEx","identifier":"coinex","has_trading_incentive":false},"last":0.0941,"volume":85475.49828294,"converted_last":{"btc":3.08e-06,"eth":4.884e-05,"usd":0.09407},"converted_volume":{"btc":0.25253893,"eth":4.010796,"usd":7724.34},"trust_score":"green","bid_ask_spread_percentage":2.10084,"timestamp":"2023-07-01T12:26:28+00:00","last_traded_at":"2023-07-01T12:26:28+00:00","last_fetch_at":"2023-07-01T12:26:28+00:00","is_anomaly":false,"is_stale":false,"trade_url":"https://www.coinex.com/trading?currency=USDT\u0026dest=EVMOS#limit","token_info_url":null,"coin_id":"evmos","target_coin_id":"tether"},{"base":"0X50DE24B3F0B3136C50FA8A3B8EBC8BD80A269CE5","target":"0XD4949664CD82660AAE99BEDC034A0DEA8A0BD517","market":{"name":"SpaceFi","identifier":"spacefi","has_trading_incentive":false},"last":20544.4213236717,"volume":2.0588627327938225,"converted_last":{"btc":3.11e-06,"eth":4.934e-05,"usd":0.095019},"converted_volume":{"btc":0.13475483,"eth":2.139724,"usd":4120.97},"trust_score":"yellow","bid_ask_spread_percentage":0.61955,"timestamp":"2023-07-01T10:35:33+00:00","last_traded_at":"2023-07-01T10:35:33+00:00","last_fetch_at":"2023-07-01T12:25:40+00:00","is_anomaly":false,"is_stale":false,"trade_url":"https://swap-evmos.spacefi.io/#/swap?inputCurrency=0x50de24b3f0b3136c50fa8a3b8ebc8bd80a269ce5\u0026outputCurrency=0xd4949664cd82660aae99bedc034a0dea8a0bd517","token_info_url":null,"coin_id":"axlweth","target_coin_id":"evmos"},{"base":"0XF5B24C0093B65408ACE53DF7CE86A02448D53B25","target":"0XD4949664CD82660AAE99BEDC034A0DEA8A0BD517","market":{"name":"SpaceFi","identifier":"spacefi","has_trading_incentive":false},"last":326943.744898055,"volume":0.01842597,"converted_last":{"btc":3.11e-06,"eth":4.934e-05,"usd":0.095019},"converted_volume":{"btc":0.01919846,"eth":0.30484547,"usd":587.11},"trust_score":"yellow","bid_ask_spread_percentage":0.621581,"timestamp":"2023-07-01T11:20:22+00:00","last_traded_at":"2023-07-01T11:20:22+00:00","last_fetch_at":"2023-07-01T12:25:40+00:00","is_anomaly":false,"is_stale":false,"trade_url":"https://swap-evmos.spacefi.io/#/swap?inputCurrency=0xf5b24c0093b65408ace53df7ce86a02448d53b25\u0026outputCurrency=0xd4949664cd82660aae99bedc034a0dea8a0bd517","token_info_url":null,"coin_id":"axlwbtc","target_coin_id":"evmos"},{"base":"0XD4949664CD82660AAE99BEDC034A0DEA8A0BD517","target":"0X5FD55A1B9FC24967C4DB09C513C3BA0DFA7FF687","market":{"name":"Diffusion Finance","identifier":"diffusion","has_trading_incentive":false},"last":0.0923645569477523,"volume":119.80549829273465,"converted_last":{"btc":3.02e-06,"eth":4.793e-05,"usd":0.092339},"converted_volume":{"btc":0.00036044,"eth":0.00572286,"usd":11.02},"trust_score":"yellow","bid_ask_spread_percentage":0.7778,"timestamp":"2023-07-01T09:10:16+00:00","last_traded_at":"2023-07-01T09:10:16+00:00","last_fetch_at":"2023-07-01T12:24:46+00:00","is_anomaly":false,"is_stale":false,"trade_url":"https://app.diffusion.fi/#/swap?inputCurrency=0xd4949664cd82660aae99bedc034a0dea8a0bd517\u0026outputCurrency=0x5fd55a1b9fc24967c4db09c513c3ba0dfa7ff687","token_info_url":null,"coin_id":"evmos","target_coin_id":"gravity-bridge-usdc"},{"base":"0X3452E23F9C4CC62C70B7ADAD699B264AF3549C19","target":"0XD4949664CD82660AAE99BEDC034A0DEA8A0BD517","market":{"name":"SpaceFi","identifier":"spacefi","has_trading_incentive":false},"last":2.85322784857782,"volume":283.489031,"converted_last":{"btc":3.11e-06,"eth":4.934e-05,"usd":0.095019},"converted_volume":{"btc":0.00254843,"eth":0.0404656,"usd":77.93},"trust_score":"yellow","bid_ask_spread_percentage":0.809586,"timestamp":"2023-07-01T07:45:51+00:00","last_traded_at":"2023-07-01T07:45:51+00:00","last_fetch_at":"2023-07-01T12:25:40+00:00","is_anomaly":false,"is_stale":false,"trade_url":"https://swap-evmos.spacefi.io/#/swap?inputCurrency=0x3452e23f9c4cc62c70b7adad699b264af3549c19\u0026outputCurrency=0xd4949664cd82660aae99bedc034a0dea8a0bd517","token_info_url":null,"coin_id":"juno-network","target_coin_id":"evmos"},{"base":"0X50DE24B3F0B3136C50FA8A3B8EBC8BD80A269CE5","target":"0XD4949664CD82660AAE99BEDC034A0DEA8A0BD517","market":{"name":"Diffusion Finance","identifier":"diffusion","has_trading_incentive":false},"last":20554.764292048,"volume":0.028413484259397014,"converted_last":{"btc":3.02e-06,"eth":4.793e-05,"usd":0.092339},"converted_volume":{"btc":0.00179968,"eth":0.02857396,"usd":55.04},"trust_score":"yellow","bid_ask_spread_percentage":0.887251,"timestamp":"2023-07-01T10:35:08+00:00","last_traded_at":"2023-07-01T10:35:08+00:00","last_fetch_at":"2023-07-01T12:24:46+00:00","is_anomaly":false,"is_stale":false,"trade_url":"https://app.diffusion.fi/#/swap?inputCurrency=0x50de24b3f0b3136c50fa8a3b8ebc8bd80a269ce5\u0026outputCurrency=0xd4949664cd82660aae99bedc034a0dea8a0bd517","token_info_url":null,"coin_id":"axlweth","target_coin_id":"evmos"},{"base":"0X3F75CEABCDFED1ACA03257DC6BDC0408E2B4B026","target":"0XD4949664CD82660AAE99BEDC034A0DEA8A0BD517","market":{"name":"Diffusion Finance","identifier":"diffusion","has_trading_incentive":false},"last":0.0029810388655657,"volume":9650.638614778114,"converted_last":{"btc":3.11e-06,"eth":4.933e-05,"usd":0.095032},"converted_volume":{"btc":8.925e-05,"eth":0.00141698,"usd":2.73},"trust_score":"red","bid_ask_spread_percentage":0.723778,"timestamp":"2023-07-01T10:23:46+00:00","last_traded_at":"2023-07-01T10:23:46+00:00","last_fetch_at":"2023-07-01T12:24:46+00:00","is_anomaly":false,"is_stale":false,"trade_url":"https://app.diffusion.fi/#/swap?inputCurrency=0x3f75ceabcdfed1aca03257dc6bdc0408e2b4b026\u0026outputCurrency=0xd4949664cd82660aae99bedc034a0dea8a0bd517","token_info_url":null,"coin_id":"diffusion","target_coin_id":"evmos"},{"base":"0X153A59D48ACEABEDBDCF7A13F67AE52B434B810B","target":"0XD4949664CD82660AAE99BEDC034A0DEA8A0BD517","market":{"name":"Diffusion Finance","identifier":"diffusion","has_trading_incentive":false},"last":19366.8948410367,"volume":0.000761740980132407,"converted_last":{"btc":3.02e-06,"eth":4.793e-05,"usd":0.092339},"converted_volume":{"btc":4.472e-05,"eth":0.00071005,"usd":1.37},"trust_score":"red","bid_ask_spread_percentage":0.969204,"timestamp":"2023-07-01T09:48:08+00:00","last_traded_at":"2023-07-01T09:48:08+00:00","last_fetch_at":"2023-07-01T12:24:46+00:00","is_anomaly":false,"is_stale":false,"trade_url":"https://app.diffusion.fi/#/swap?inputCurrency=0x153a59d48aceabedbdcf7a13f67ae52b434b810b\u0026outputCurrency=0xd4949664cd82660aae99bedc034a0dea8a0bd517","token_info_url":null,"coin_id":"wrapped-ether-celer","target_coin_id":"evmos"},{"base":"EVMOS","target":"USDT","market":{"name":"BingX","identifier":"bingx","has_trading_incentive":false},"last":0.092,"volume":262445.989503,"converted_last":{"btc":3.01e-06,"eth":4.772e-05,"usd":0.091902},"converted_volume":{"btc":0.7784877,"eth":12.36133,"usd":23807},"trust_score":null,"bid_ask_spread_percentage":5.779154,"timestamp":"2023-07-01T12:25:19+00:00","last_traded_at":"2023-07-01T12:25:19+00:00","last_fetch_at":"2023-07-01T12:25:19+00:00","is_anomaly":false,"is_stale":false,"trade_url":"https://bingx.com/en-us/spot/EVMOSUSDT","token_info_url":null,"coin_id":"evmos","target_coin_id":"tether"},{"base":"0XC5E00D3B04563950941F7137B5AFA3A534F0D6D6","target":"0XD4949664CD82660AAE99BEDC034A0DEA8A0BD517","market":{"name":"SpaceFi","identifier":"spacefi","has_trading_incentive":false},"last":100.399807481882,"volume":694.697426,"converted_last":{"btc":3.11e-06,"eth":4.934e-05,"usd":0.095019},"converted_volume":{"btc":0.21701363,"eth":3.445882,"usd":6636.55},"trust_score":null,"bid_ask_spread_percentage":0.611371,"timestamp":"2023-07-01T12:17:56+00:00","last_traded_at":"2023-07-01T12:17:56+00:00","last_fetch_at":"2023-07-01T12:25:39+00:00","is_anomaly":true,"is_stale":false,"trade_url":"https://swap-evmos.spacefi.io/#/swap?inputCurrency=0xc5e00d3b04563950941f7137b5afa3a534f0d6d6\u0026outputCurrency=0xd4949664cd82660aae99bedc034a0dea8a0bd517","token_info_url":null,"coin_id":"cosmos","target_coin_id":"evmos"},{"base":"0XC5E00D3B04563950941F7137B5AFA3A534F0D6D6","target":"0XD4949664CD82660AAE99BEDC034A0DEA8A0BD517","market":{"name":"Diffusion Finance","identifier":"diffusion","has_trading_incentive":false},"last":100.763596522263,"volume":33.623441,"converted_last":{"btc":3.11e-06,"eth":4.933e-05,"usd":0.095032},"converted_volume":{"btc":0.01054807,"eth":0.16747476,"usd":322.62},"trust_score":null,"bid_ask_spread_percentage":0.662015,"timestamp":"2023-07-01T12:11:17+00:00","last_traded_at":"2023-07-01T12:11:17+00:00","last_fetch_at":"2023-07-01T12:24:46+00:00","is_anomaly":true,"is_stale":false,"trade_url":"https://app.diffusion.fi/#/swap?inputCurrency=0xc5e00d3b04563950941f7137b5afa3a534f0d6d6\u0026outputCurrency=0xd4949664cd82660aae99bedc034a0dea8a0bd517","token_info_url":null,"coin_id":"cosmos","target_coin_id":"evmos"},{"base":"0X47685B6AC7BB4DE761A57828877A7B8254C8B145","target":"0XD4949664CD82660AAE99BEDC034A0DEA8A0BD517","market":{"name":"Diffusion Finance","identifier":"diffusion","has_trading_incentive":false},"last":0.0113976757895896,"volume":3876.7674983516476,"converted_last":{"btc":3.02e-06,"eth":4.793e-05,"usd":0.092339},"converted_volume":{"btc":0.00013388,"eth":0.0021257,"usd":4.09},"trust_score":"red","bid_ask_spread_percentage":0.825289,"timestamp":"2023-07-01T00:06:43+00:00","last_traded_at":"2023-07-01T00:06:43+00:00","last_fetch_at":"2023-07-01T12:24:46+00:00","is_anomaly":false,"is_stale":true,"trade_url":"https://app.diffusion.fi/#/swap?inputCurrency=0x47685b6ac7bb4de761a57828877a7b8254c8b145\u0026outputCurrency=0xd4949664cd82660aae99bedc034a0dea8a0bd517","token_info_url":null,"coin_id":"evmos-domains","target_coin_id":"evmos"},{"base":"0XD4949664CD82660AAE99BEDC034A0DEA8A0BD517","target":"0XD567B3D7B8FE3C79A1AD8DA978812CFC4FA05E75","market":{"name":"Diffusion Finance","identifier":"diffusion","has_trading_incentive":false},"last":0.0951674295528695,"volume":11.4666398503814,"converted_last":{"btc":3.02e-06,"eth":4.793e-05,"usd":0.092339},"converted_volume":{"btc":3.462e-05,"eth":0.00054965,"usd":1.059},"trust_score":"red","bid_ask_spread_percentage":0.889977,"timestamp":"2023-06-30T16:03:27+00:00","last_traded_at":"2023-06-30T16:03:27+00:00","last_fetch_at":"2023-07-01T12:24:46+00:00","is_anomaly":false,"is_stale":true,"trade_url":"https://app.diffusion.fi/#/swap?inputCurrency=0xd4949664cd82660aae99bedc034a0dea8a0bd517\u0026outputCurrency=0xd567b3d7b8fe3c79a1ad8da978812cfc4fa05e75","token_info_url":null,"coin_id":"evmos","target_coin_id":"gravity-bridge-dai"},{"base":"EVMOS","target":"AXLUSDC","market":{"name":"Kujira Fin","identifier":"kujira","has_trading_incentive":false},"last":0.067,"volume":2.000641791,"converted_last":{"btc":2.2e-06,"eth":3.463e-05,"usd":0.066935},"converted_volume":{"btc":4.39e-06,"eth":6.928e-05,"usd":0.133913},"trust_score":null,"bid_ask_spread_percentage":73.2,"timestamp":"2023-06-29T23:53:26+00:00","last_traded_at":"2023-06-29T23:53:26+00:00","last_fetch_at":"2023-06-30T23:49:36+00:00","is_anomaly":false,"is_stale":true,"trade_url":"https://fin.kujira.app/trade/kujira182nff4ttmvshn6yjlqj5czapfcav9434l2qzz8aahf5pxnyd33tsz30aw6","token_info_url":null,"coin_id":"evmos","target_coin_id":"axlusdc"},{"base":"CMST","target":"EVMOS","market":{"name":"cSwap","identifier":"cswap","has_trading_incentive":false},"last":10.908,"volume":3.070912,"converted_last":{"btc":3.0e-06,"eth":4.725e-05,"usd":0.091469},"converted_volume":{"btc":9.606e-05,"eth":0.00151275,"usd":2.93},"trust_score":null,"bid_ask_spread_percentage":null,"timestamp":"2023-06-30T15:38:28+00:00","last_traded_at":"2023-06-30T15:38:28+00:00","last_fetch_at":"2023-06-30T23:32:47+00:00","is_anomaly":false,"is_stale":true,"trade_url":"https://app.cswap.one/trade","token_info_url":null,"coin_id":"composite","target_coin_id":"evmos"},{"base":"CMDX","target":"EVMOS","market":{"name":"cSwap","identifier":"cswap","has_trading_incentive":false},"last":0.32382,"volume":0.620748,"converted_last":{"btc":3.33e-06,"eth":5.416e-05,"usd":0.099996},"converted_volume":{"btc":6.68728e-07,"eth":1.088e-05,"usd":0.02009557},"trust_score":null,"bid_ask_spread_percentage":null,"timestamp":"2023-06-30T14:33:25+00:00","last_traded_at":"2023-06-30T14:33:25+00:00","last_fetch_at":"2023-06-30T15:33:51+00:00","is_anomaly":false,"is_stale":true,"trade_url":"https://app.cswap.one/trade","token_info_url":null,"coin_id":"comdex","target_coin_id":"evmos"},{"base":"EVMOS","target":"USDT","market":{"name":"Helix","identifier":"injective","has_trading_incentive":false},"last":0.0507,"volume":0.19999999999999998,"converted_last":{"btc":1.67e-06,"eth":2.742e-05,"usd":0.050676},"converted_volume":{"btc":3.33576e-07,"eth":5.48e-06,"usd":0.0101353},"trust_score":null,"bid_ask_spread_percentage":87.203433,"timestamp":"2023-06-29T08:23:44+00:00","last_traded_at":"2023-06-29T08:23:44+00:00","last_fetch_at":"2023-06-29T08:23:44+00:00","is_anomaly":true,"is_stale":true,"trade_url":"https://helixapp.com/","token_info_url":null,"coin_id":"evmos","target_coin_id":"tether"}]}